d666_rpg_system/__init__.py
d666_rpg_system/char.py
d666_rpg_system/data.py
d666_rpg_system-0.1.1.dist-info/LICENSE
d666_rpg_system-0.1.1.dist-info/METADATA
d666_rpg_system-0.1.1.dist-info/WHEEL
d666_rpg_system-0.1.1.dist-info/top_level.txt
d666_rpg_system-0.1.1.dist-info/RECORD
