Metadata-Version: 2.1
Name: d666_rpg_system
Version: 0.1.1
Summary: The d666 RPG System
Author: Jeremy Deram
License: This game is released under the CC BY-SA 4.0 license.
Project-URL: homepage, https://github.com/jderam/d666-rpg-system
Keywords: d666,RPG,Dungeons,Dragons
Classifier: Programming Language :: Python :: 3
Classifier: Programming Language :: Python :: 3 :: Only
Classifier: Programming Language :: Python :: 3.8
Classifier: Programming Language :: Python :: 3.9
Classifier: Programming Language :: Python :: 3.10
Classifier: Programming Language :: Python :: 3.11
Classifier: Operating System :: OS Independent
Requires-Python: >=3.8
License-File: LICENSE
Provides-Extra: dev
Requires-Dist: build ; extra == 'dev'
Requires-Dist: pre-commit ; extra == 'dev'
Requires-Dist: pytest ; extra == 'dev'
Requires-Dist: pytest-cov ; extra == 'dev'
Requires-Dist: ruff ; extra == 'dev'
Requires-Dist: twine ; extra == 'dev'
